<?xml version="1.0" encoding="utf-8"?>
<openerp>
    <data>
        
        
        
<!--	^^^^^^^^^^^^^^^^^^^^^^^^^^^^^^^^^^^^^^
       			Invoice: Transfers 
  		^^^^^^^^^^^^^^^^^^^^^^^^^^^^^^^^^^^^^^	
--> 
        
        <record id="view_invoice_car_tree" model="ir.ui.view">
            <field name="name">view.invoice.car.tree</field>
            <field name="model">tr.invoice.car</field>
            <field name="type">tree</field>
            <field name="arch" type="xml">
                <tree string="Transfers">
                    <field name="tpartner_id"/> 
                    <field name="name"/>
                    <field name="subtotal" string="Basic+Other"/> 
                    <field name="taxes"/>
                    <field name="total"/>
                    <field name="currency_id"/>
                    <button name="print_voucher" type="object" icon="gtk-jump-to" help="Print Voucher"/>
                </tree>
            </field>
        </record>
        
        
        <record id="view_invoice_car_form" model="ir.ui.view">
            <field name="name">view.invoice.car.form</field>
            <field name="model">tr.invoice.car</field>
            <field name="type">form</field>
            <field name="arch" type="xml">
                <form string="Transfers" version="7.0">
                    <group col="6" colspan="3">
                        <field name="tpartner_id" context="{'search_default_supplier':1,'default_supplier':1,'default_customer':0}"/> 
                        <field name="product_id" on_change="onchange_product(product_id)" context="{'default_travel_type':context.get('travel_type')}"/>
                        <field name="name"/>
                        <field name="currency_id"/> 
                    </group>   
                  <notebook>
                  	<page string= "Passenger">
                  		<u><separator string="Customer Details"/></u>
	                    <group col="6" colspan="3">
	                    	<field name="pax_id" on_change="onchange_passenger(pax_id)"/>
	                        <field name="pax_name" nolabel="1"/>
	                        <field name="pax_ph"/>
	                        <newline/>
	                        <field name="pax_email"/>
	                    </group>
	                    <notebook>
                        <page string="Pick Up">
                            <field name="pick_up"/>
                        </page>
                        <page string="Drop At">
                            <field name="drop_at"/>
                        </page>
                        <page string="Route">
                            <field name="route"/>
                        </page>
                        <page string="Inclusive">
                            <field name="incl"/>
                        </page>
                        <page string="Remarks">
                            <field name="remarks"/>
                        </page>
                        <page string="Cost Details">
                            <field name="details"/>
                        </page>
                    </notebook>
                    </page>
                    <page string= "Fare Details">
                    	<u><separator string="Vehicle Details"/></u>
	                    <group col="6" colspan="3">
	                        <field name="vehicle_id"     on_change="onchange_CAR_Basic(cost_type, no_kms, no_days, usage_lmt, rate_km, ext_rate_km, ext_hr_trvld, ext_rate_hour,  mrkup_km, ext_mrkup_km, ext_mrkup_hour)"/>
	                        <field name="start_dt"       on_change="onchange_start_dt(start_dt)"/>
	                        <field name="end_dt"	     on_change="onchange_start_dt(start_dt)"/>
	                        <field name="cost_type"      on_change="onchange_CAR_Basic(cost_type, no_kms, no_days, usage_lmt, rate_km, ext_rate_km, ext_hr_trvld, ext_rate_hour,  mrkup_km, ext_mrkup_km, ext_mrkup_hour)"/>
	                        <field name="no_vehicle"     on_change="onchange_CAR_total(inv_type, 'all', no_vehicle, basic, tac_perc, tac, markup_perc, markup, tds_perc, tds, other, driver_chrgs,  discount, tds1_perc, tds1, servicechrg_perc, servicechrg, cancel_markup, cancel_charges, cancel_service, tptax_basic, tptax_tac, tptax_tds, tptax_other, tptax_ids, cost_on, False, context)"/>
	                        <field name="no_days"        on_change="onchange_CAR_Basic(cost_type, no_kms, no_days, usage_lmt, rate_km, ext_rate_km, ext_hr_trvld, ext_rate_hour,  mrkup_km, ext_mrkup_km, ext_mrkup_hour)"/>
	                        <field name="no_kms"         on_change="onchange_CAR_Basic(cost_type, no_kms, no_days, usage_lmt, rate_km, ext_rate_km, ext_hr_trvld, ext_rate_hour,  mrkup_km, ext_mrkup_km, ext_mrkup_hour)"/>
	                        <field name="usage_lmt"      on_change="onchange_CAR_Basic(cost_type, no_kms, no_days, usage_lmt, rate_km, ext_rate_km, ext_hr_trvld, ext_rate_hour,  mrkup_km, ext_mrkup_km, ext_mrkup_hour)"/>
	                        <field name="ext_km_trvld"   on_change="onchange_CAR_Basic(cost_type, no_kms, no_days, usage_lmt, rate_km, ext_rate_km, ext_hr_trvld, ext_rate_hour,  mrkup_km, ext_mrkup_km, ext_mrkup_hour)"/>
	                        <field name="rate_km"        on_change="onchange_CAR_Basic(cost_type, no_kms, no_days, usage_lmt, rate_km, ext_rate_km, ext_hr_trvld, ext_rate_hour,  mrkup_km, ext_mrkup_km, ext_mrkup_hour)"/>
	                        <field name="mrkup_km"       on_change="onchange_CAR_Basic(cost_type, no_kms, no_days, usage_lmt, rate_km, ext_rate_km, ext_hr_trvld, ext_rate_hour,  mrkup_km, ext_mrkup_km, ext_mrkup_hour)"/>
	                        <field name="driver_chrgs"   on_change="onchange_CAR_total(inv_type, 'all', no_vehicle, basic, tac_perc, tac, markup_perc, markup, tds_perc, tds, other, driver_chrgs,  discount, tds1_perc, tds1, servicechrg_perc, servicechrg, cancel_markup, cancel_charges, cancel_service, tptax_basic, tptax_tac, tptax_tds, tptax_other, tptax_ids, cost_on, False, context)"/>
	                        <field name="ext_rate_km"    on_change="onchange_CAR_Basic(cost_type, no_kms, no_days, usage_lmt, rate_km, ext_rate_km, ext_hr_trvld, ext_rate_hour,  mrkup_km, ext_mrkup_km, ext_mrkup_hour)"/>
	                        <field name="ext_mrkup_km"   on_change="onchange_CAR_Basic(cost_type, no_kms, no_days, usage_lmt, rate_km, ext_rate_km, ext_hr_trvld, ext_rate_hour,  mrkup_km, ext_mrkup_km, ext_mrkup_hour)"/>
	                        <newline/>
	                        <field name="ext_rate_hour"  on_change="onchange_CAR_Basic(cost_type, no_kms, no_days, usage_lmt, rate_km, ext_rate_km, ext_hr_trvld, ext_rate_hour,  mrkup_km, ext_mrkup_km, ext_mrkup_hour)"/>
	                        <field name="ext_hr_trvld"   on_change="onchange_CAR_Basic(cost_type, no_kms, no_days, usage_lmt, rate_km, ext_rate_km, ext_hr_trvld, ext_rate_hour,  mrkup_km, ext_mrkup_km, ext_mrkup_hour)"/>
	                        <field name="ext_mrkup_hour" on_change="onchange_CAR_Basic(cost_type, no_kms, no_days, usage_lmt, rate_km, ext_rate_km, ext_hr_trvld, ext_rate_hour,  mrkup_km, ext_mrkup_km, ext_mrkup_hour)"/>
	                        <field name="driver"/>
	                        <field name="driver_ph"/>
	                        <field name="inv_type" invisible="1"/>
	                    </group>
	                    <u><separator string="Fare Details"/></u>
	                    <group col="6" colspan="3">
	                        <field name="basic"            on_change="onchange_CAR_total(inv_type, 'all', no_vehicle, basic, tac_perc, tac, markup_perc, markup, tds_perc, tds, other, driver_chrgs,  discount, tds1_perc, tds1, servicechrg_perc, servicechrg, cancel_markup, cancel_charges, cancel_service, tptax_basic, tptax_tac, tptax_tds, tptax_other, tptax_ids, cost_on, False, context)"/> 
	                        <field name="tac_perc"         on_change="onchange_CAR_total(inv_type, 'all', no_vehicle, basic, tac_perc, tac, markup_perc, markup, tds_perc, tds, other, driver_chrgs,  discount, tds1_perc, tds1, servicechrg_perc, servicechrg, cancel_markup, cancel_charges, cancel_service, tptax_basic, tptax_tac, tptax_tds, tptax_other, tptax_ids, cost_on, False, context)"/> 
	                        <field name="tac"              on_change="onchange_CAR_total(inv_type, 'amt', no_vehicle, basic, tac_perc, tac, markup_perc, markup, tds_perc, tds, other, driver_chrgs,  discount, tds1_perc, tds1, servicechrg_perc, servicechrg, cancel_markup, cancel_charges, cancel_service, tptax_basic, tptax_tac, tptax_tds, tptax_other, tptax_ids, cost_on, False, context)" class="trab_maroon_css"/>
	                        <field name="tptax"/>
	                        <field name="tds_perc"         on_change="onchange_CAR_total(inv_type, 'all', no_vehicle, basic, tac_perc, tac, markup_perc, markup, tds_perc, tds, other, driver_chrgs,  discount, tds1_perc, tds1, servicechrg_perc, servicechrg, cancel_markup, cancel_charges, cancel_service, tptax_basic, tptax_tac, tptax_tds, tptax_other, tptax_ids, cost_on, False, context)"/>
	                        <field name="tds"              on_change="onchange_CAR_total(inv_type, 'amt', no_vehicle, basic, tac_perc, tac, markup_perc, markup, tds_perc, tds, other, driver_chrgs,  discount, tds1_perc, tds1, servicechrg_perc, servicechrg, cancel_markup, cancel_charges, cancel_service, tptax_basic, tptax_tac, tptax_tds, tptax_other, tptax_ids, cost_on, False, context)" class="trab_maroon_css"/>
	                         <field name="other" 		   on_change="onchange_CAR_total(inv_type, 'all', no_vehicle, basic, tac_perc, tac, markup_perc, markup, tds_perc, tds, other, driver_chrgs,  discount, tds1_perc, tds1, servicechrg_perc, servicechrg, cancel_markup, cancel_charges, cancel_service, tptax_basic, tptax_tac, tptax_tds, tptax_other, tptax_ids, cost_on, False, context)"/>
	                        <field name="markup_perc"      on_change="onchange_CAR_total(inv_type, 'all', no_vehicle, basic, tac_perc, tac, markup_perc, markup, tds_perc, tds, other, driver_chrgs,  discount, tds1_perc, tds1, servicechrg_perc, servicechrg, cancel_markup, cancel_charges, cancel_service, tptax_basic, tptax_tac, tptax_tds, tptax_other, tptax_ids, cost_on, False, context)"/>
	                        <field name="markup"           on_change="onchange_CAR_total(inv_type, 'amt', no_vehicle, basic, tac_perc, tac, markup_perc, markup, tds_perc, tds, other, driver_chrgs,  discount, tds1_perc, tds1, servicechrg_perc, servicechrg, cancel_markup, cancel_charges, cancel_service, tptax_basic, tptax_tac, tptax_tds, tptax_other, tptax_ids, cost_on, False, context)" class="trab_maroon_css"/>
	                        <field name="discount" 		   on_change="onchange_CAR_total(inv_type, 'all', no_vehicle, basic, tac_perc, tac, markup_perc, markup, tds_perc, tds, other, driver_chrgs,  discount, tds1_perc, tds1, servicechrg_perc, servicechrg, cancel_markup, cancel_charges, cancel_service, tptax_basic, tptax_tac, tptax_tds, tptax_other, tptax_ids, cost_on, False, context)"/>
	                        <field name="tds1_perc" 	   on_change="onchange_CAR_total(inv_type, 'all', no_vehicle, basic, tac_perc, tac, markup_perc, markup, tds_perc, tds, other, driver_chrgs,  discount, tds1_perc, tds1, servicechrg_perc, servicechrg, cancel_markup, cancel_charges, cancel_service, tptax_basic, tptax_tac, tptax_tds, tptax_other, tptax_ids, cost_on, False, context)"/>
	                        <field name="tds1" 			   on_change="onchange_CAR_total(inv_type, 'amt', no_vehicle, basic, tac_perc, tac, markup_perc, markup, tds_perc, tds, other, driver_chrgs,  discount, tds1_perc, tds1, servicechrg_perc, servicechrg, cancel_markup, cancel_charges, cancel_service, tptax_basic, tptax_tac, tptax_tds, tptax_other, tptax_ids, cost_on, False, context)" class="trab_maroon_css"/>
	                        <field name="servicechrg_perc" on_change="onchange_CAR_total(inv_type, 'all', no_vehicle, basic, tac_perc, tac, markup_perc, markup, tds_perc, tds, other, driver_chrgs,  discount, tds1_perc, tds1, servicechrg_perc, servicechrg, cancel_markup, cancel_charges, cancel_service, tptax_basic, tptax_tac, tptax_tds, tptax_other, tptax_ids, cost_on, False, context)"/> 
	                        <field name="servicechrg"      on_change="onchange_CAR_total(inv_type, 'amt', no_vehicle, basic, tac_perc, tac, markup_perc, markup, tds_perc, tds, other, driver_chrgs,  discount, tds1_perc, tds1, servicechrg_perc, servicechrg, cancel_markup, cancel_charges, cancel_service, tptax_basic, tptax_tac, tptax_tds, tptax_other, tptax_ids, cost_on, True, context)" class="trab_maroon_css"/>
	                        <field name="cancel_markup"    on_change="onchange_CAR_total(inv_type, 'all', no_vehicle, basic, tac_perc, tac, markup_perc, markup, tds_perc, tds, other, driver_chrgs,  discount, tds1_perc, tds1, servicechrg_perc, servicechrg, cancel_markup, cancel_charges, cancel_service, tptax_basic, tptax_tac, tptax_tds, tptax_other, tptax_ids, cost_on, False, context)" invisible="not context.get('credit_view')" class="trab_maroon_css"/>
	                        <field name="cancel_charges"   on_change="onchange_CAR_total(inv_type, 'all', no_vehicle, basic, tac_perc, tac, markup_perc, markup, tds_perc, tds, other, driver_chrgs,  discount, tds1_perc, tds1, servicechrg_perc, servicechrg, cancel_markup, cancel_charges, cancel_service, tptax_basic, tptax_tac, tptax_tds, tptax_other, tptax_ids, cost_on, False, context)" invisible="not context.get('credit_view')" class="trab_maroon_css"/>
	                        <field name="cancel_service"   on_change="onchange_CAR_total(inv_type, 'all', no_vehicle, basic, tac_perc, tac, markup_perc, markup, tds_perc, tds, other, driver_chrgs,  discount, tds1_perc, tds1, servicechrg_perc, servicechrg, cancel_markup, cancel_charges, cancel_service, tptax_basic, tptax_tac, tptax_tds, tptax_other, tptax_ids, cost_on, False, context)" invisible="not context.get('credit_view')" class="trab_maroon_css"/> 
	                        <field name="subtotal" class="trab_boldc_css"/> 
	                    </group>
	                    <u><separator string="Tax Details"/></u>
                    <notebook>
                        <page string="T P Tax">
                            <group col="8" colspan="4">                    			
                                <field name="tptax_basic" 	on_change="onchange_CAR_total(inv_type, 'all', no_vehicle, basic, tac_perc, tac, markup_perc, markup, tds_perc, tds, other, driver_chrgs,  discount, tds1_perc, tds1, servicechrg_perc, servicechrg, cancel_markup, cancel_charges, cancel_service, tptax_basic, tptax_tac, tptax_tds, tptax_other, tptax_ids, cost_on, False, context)"/> 
                                <field name="tptax_other" 	on_change="onchange_CAR_total(inv_type, 'all', no_vehicle, basic, tac_perc, tac, markup_perc, markup, tds_perc, tds, other, driver_chrgs,  discount, tds1_perc, tds1, servicechrg_perc, servicechrg, cancel_markup, cancel_charges, cancel_service, tptax_basic, tptax_tac, tptax_tds, tptax_other, tptax_ids, cost_on, False, context)"/> 
                                <field name="tptax_tac"  	on_change="onchange_CAR_total(inv_type, 'all', no_vehicle, basic, tac_perc, tac, markup_perc, markup, tds_perc, tds, other, driver_chrgs,  discount, tds1_perc, tds1, servicechrg_perc, servicechrg, cancel_markup, cancel_charges, cancel_service, tptax_basic, tptax_tac, tptax_tds, tptax_other, tptax_ids, cost_on, False, context)"/>
                                <field name="tptax_tds" 	on_change="onchange_CAR_total(inv_type, 'all', no_vehicle, basic, tac_perc, tac, markup_perc, markup, tds_perc, tds, other, driver_chrgs,  discount, tds1_perc, tds1, servicechrg_perc, servicechrg, cancel_markup, cancel_charges, cancel_service, tptax_basic, tptax_tac, tptax_tds, tptax_other, tptax_ids, cost_on, False, context)"/>
                                <field name="tptax_ids" colspan="4" widget="many2many_tags" 
                                    on_change="onchange_CAR_total(inv_type, 'all', no_vehicle, basic, tac_perc, tac, markup_perc, markup, tds_perc, tds, other, driver_chrgs,  discount, tds1_perc, tds1, servicechrg_perc, servicechrg, cancel_markup, cancel_charges, cancel_service, tptax_basic, tptax_tac, tptax_tds, tptax_other, tptax_ids, cost_on, False, context)"/>
                            </group>
                        </page>
                        <page string="TAX">
                            <group col="8" colspan="4">
                                <field name="tax_basic" 		class="trab_maroon_css"/> 
                                <field name="tax_tac" 			class="trab_maroon_css"/>
                                <field name="tax_tds" 			class="trab_maroon_css"/> 
                                <field name="tax_tds1" 			class="trab_maroon_css"/>                    			
                                <field name="tax_mark" 			class="trab_maroon_css"/>
                                <field name="tax_other" 		class="trab_maroon_css"/> 
                                <field name="tax_tptax" 		class="trab_maroon_css"/>
                                <field name="tax_servicechrg" 	class="trab_maroon_css"/> 
                                <field name="tax_ids" colspan="4" widget="many2many_tags" class="trab_maroon_css"/>                    		
                            </group>
                        </page>
                    </notebook>
                        <u><separator string="Passenger Fares :"/></u>
                        <group col="6" colspan="3">
                            <field name="cost_on" colspan="3" on_change="onchange_CAR_total(inv_type, 'all', no_vehicle, basic, tac_perc, tac, markup_perc, markup, tds_perc, tds, other, driver_chrgs,  discount, tds1_perc, tds1, servicechrg_perc, servicechrg, cancel_markup, cancel_charges, cancel_service, tptax_basic, tptax_tac, tptax_tds, tptax_other, tptax_ids, cost_on, False, context)"/>
                        </group>
                        <group col="8" colspan="4">
                            <field name="a_rate" class="trab_boldc_css"/>
                            <field name="e_rate" class="trab_boldc_css"/> 
                            <field name="c_rate" class="trab_boldc_css"/>        
                            <field name="i_rate" class="trab_boldc_css"/>          
                        </group>
                    </page>
                  </notebook>
                </form>
            </field>
        </record>
        
    </data>
</openerp>